pyasstosrt-1.5.0.dist-info/METADATA
pyasstosrt-1.5.0.dist-info/WHEEL
pyasstosrt-1.5.0.dist-info/entry_points.txt
pyasstosrt-1.5.0.dist-info/licenses/LICENSE
pyasstosrt/__init__.py
pyasstosrt/batch.py
pyasstosrt/dialogue.py
pyasstosrt/pyasstosrt.py
pyasstosrt/time.py
pyasstosrt-1.5.0.dist-info/RECORD
