Metadata-Version: 2.1
Name: pyasstosrt
Version: 1.5.0
Summary: Convert ASS subtitle to SRT format
Keywords: ASS subtitle,SRT,Convert,subtitle,subtitles,Advanced SubStation Alpha,SubRip,conversion,subtitle conversion,caption,captions,batch conversion,video,media,CLI
Author-Email: GitBib <me@bnff.website>
License: Apache License, Version 2.0
Classifier: Operating System :: OS Independent
Classifier: Programming Language :: Python
Classifier: Programming Language :: Python :: 3.9
Classifier: Programming Language :: Python :: 3.10
Classifier: Programming Language :: Python :: 3.11
Classifier: Programming Language :: Python :: 3.12
Classifier: Programming Language :: Python :: 3.13
Classifier: Programming Language :: Python :: 3.14
Classifier: Programming Language :: Python :: Implementation :: PyPy
Classifier: Programming Language :: Python :: Implementation :: CPython
Project-URL: Homepage, https://github.com/GitBib/pyasstosrt
Project-URL: Repository, https://github.com/GitBib/pyasstosrt
Project-URL: Documentation, https://gitbib.github.io/pyasstosrt/
Requires-Python: >=3.9
Provides-Extra: cli
Requires-Dist: typer>=0.20.0; extra == "cli"
